pytest/__init__.py
pytest/__main__.py
pytest/__version__.py
pytest/mock.py
pytest/pytest.py
pytest/test_runner.py
ironpython_pytest-0.5.0.dist-info/AUTHORS.md
ironpython_pytest-0.5.0.dist-info/LICENSE
ironpython_pytest-0.5.0.dist-info/METADATA
ironpython_pytest-0.5.0.dist-info/WHEEL
ironpython_pytest-0.5.0.dist-info/top_level.txt
ironpython_pytest-0.5.0.dist-info/RECORD
