Metadata-Version: 2.1
Name: ironpython-pytest
Version: 0.5.0
Summary: Ridiculously minimal and incomplete pytest replacement for IronPython
Home-page: https://github.com/gramaziokohler/ironpython-pytest
Author: Gramazio Kohler Research
Author-email: gramaziokohler@arch.ethz.ch
License: MIT
Keywords: unit-testing
Platform: UNKNOWN
Classifier: Development Status :: 4 - Beta
Classifier: License :: OSI Approved :: MIT License
Classifier: Operating System :: Microsoft :: Windows
Classifier: Programming Language :: Python
Classifier: Programming Language :: Python :: 2.7
Classifier: Programming Language :: Python :: Implementation :: IronPython
Requires-Python: >=2.7
